LICENSE.txt
README.md
setup.py
clipea/__init__.py
clipea/__main__.py
clipea/cli.py
clipea/clipea.zsh
clipea/clipea_llm.py
clipea/commands.py
clipea/router.py
clipea/system-prompt.txt
clipea/usage.txt
clipea/utils.py
clipea_cli.egg-info/PKG-INFO
clipea_cli.egg-info/SOURCES.txt
clipea_cli.egg-info/dependency_links.txt
clipea_cli.egg-info/entry_points.txt
clipea_cli.egg-info/requires.txt
clipea_cli.egg-info/top_level.txt