Metadata-Version: 2.1
Name: clipea-cli
Version: 0.1.0
Summary:  📎🟢 Like Clippy but for the CLI. A blazing fast AI helper for your command line 
Home-page: https://github.com/dave1010/clipea/
Author: Dave Hulbert
Author-email: dave1010@gmail.com
License: MIT
Keywords: cli,ai,assistant,automation
Requires-Python: >=3.10
License-File: LICENSE.txt
